{"cameraMode":{"drawMode":0,"name":"Shaded","section":"Shading Mode"},"sceneLighting":true,"audioPlay":false,"sceneViewState":{"m_AlwaysRefresh":false,"showFog":true,"showSkybox":true,"showFlares":true,"showImageEffects":true,"showParticleSystems":true,"showVisualEffectGraphs":true,"m_FxEnabled":true},"in2DMode":false,"pivot":{"x":2.693812370300293,"y":0.9178272485733032,"z":14.454073905944825},"rotation":{"x":-0.11856594681739807,"y":0.6217718124389648,"z":-0.09625959396362305,"w":-0.768267810344696},"size":1.720107078552246,"orthographic":false}